CHANGES.rst
COPYRIGHT.txt
LICENSE.txt
MANIFEST.in
README.rst
setup.py
src/zc/__init__.py
src/zc.recipe.deployment.egg-info/PKG-INFO
src/zc.recipe.deployment.egg-info/SOURCES.txt
src/zc.recipe.deployment.egg-info/dependency_links.txt
src/zc.recipe.deployment.egg-info/entry_points.txt
src/zc.recipe.deployment.egg-info/namespace_packages.txt
src/zc.recipe.deployment.egg-info/not-zip-safe
src/zc.recipe.deployment.egg-info/requires.txt
src/zc.recipe.deployment.egg-info/top_level.txt
src/zc/recipe/__init__.py
src/zc/recipe/deployment/README.txt
src/zc/recipe/deployment/__init__.py
src/zc/recipe/deployment/paths.test
src/zc/recipe/deployment/tests.py