Metadata-Version: 1.0
Name: zc.recipe.deployment
Version: 1.3.0
Summary: ZC Buildout recipe for Unix deployments
Home-page: http://www.python.org/pypi/zc.recipe.deployment
Author: Jim Fulton
Author-email: jim@zope.com
License: ZPL 2.1
Keywords: deployment build
Platform: UNKNOWN
